engineering_box_sdk/__init__.py
engineering_box_sdk/main.py
engineering_box_sdk-0.1.0.dist-info/METADATA
engineering_box_sdk-0.1.0.dist-info/WHEEL
engineering_box_sdk-0.1.0.dist-info/entry_points.txt
engineering_box_sdk-0.1.0.dist-info/top_level.txt
engineering_box_sdk-0.1.0.dist-info/RECORD
